odoo/addons/attachment_category/README.rst
odoo/addons/attachment_category/__init__.py
odoo/addons/attachment_category/__manifest__.py
odoo/addons/attachment_category/i18n/attachment_category.pot
odoo/addons/attachment_category/models/__init__.py
odoo/addons/attachment_category/models/ir_attachment.py
odoo/addons/attachment_category/models/ir_attachment_category.py
odoo/addons/attachment_category/readme/CONTRIBUTORS.rst
odoo/addons/attachment_category/readme/DESCRIPTION.rst
odoo/addons/attachment_category/readme/USAGE.rst
odoo/addons/attachment_category/security/ir_attachment_category.xml
odoo/addons/attachment_category/static/description/icon.png
odoo/addons/attachment_category/static/description/index.html
odoo/addons/attachment_category/views/ir_attachment.xml
odoo/addons/attachment_category/views/ir_attachment_category.xml
odoo13_addon_attachment_category-13.0.1.0.1.dist-info/METADATA
odoo13_addon_attachment_category-13.0.1.0.1.dist-info/WHEEL
odoo13_addon_attachment_category-13.0.1.0.1.dist-info/top_level.txt
odoo13_addon_attachment_category-13.0.1.0.1.dist-info/RECORD
